random_img_api/__init__.py
random_img_api/img_api_cli.py
random_img_api/src/config/config.py
random_img_api/src/config/config_cli.py
random_img_api/src/dbo.py
random_img_api/src/get_img/downloader.py
random_img_api/src/get_img/gen_ai.py
random_img_api/src/get_img/gen_avatar.py
random_img_api/src/get_img/get_img.py
random_img_api/src/get_img/get_url.py
random_img_api/src/main.py
random_img_api/src/run.py
random_img_api-1.1.3.dist-info/entry_points.txt
random_img_api-1.1.3.dist-info/LICENSE
random_img_api-1.1.3.dist-info/WHEEL
random_img_api-1.1.3.dist-info/METADATA
random_img_api-1.1.3.dist-info/RECORD
