Metadata-Version: 2.1
Name: random-img-api
Version: 1.1.3
Summary: Random Image API
Home-page: https://github.com/BrandenXia/Random_Img_API
License: GPLv2
Author: BrandenXia
Author-email: xxtbranden@outlook.com
Requires-Python: >=3.10,<4.0
Classifier: License :: OSI Approved :: GNU General Public License v2 (GPLv2)
Classifier: License :: Other/Proprietary License
Classifier: Operating System :: OS Independent
Classifier: Programming Language :: Python :: 3
Classifier: Programming Language :: Python :: 3.10
Classifier: Programming Language :: Python :: 3.11
Classifier: Programming Language :: Python :: 3
Requires-Dist: Pillow (>=9.3.0,<10.0.0)
Requires-Dist: fastapi (>=0.87.0,<0.88.0)
Requires-Dist: gunicorn (>=20.1.0,<21.0.0)
Requires-Dist: openai (>=0.25.0,<0.26.0)
Requires-Dist: pydenticon (>=0.3.1,<0.4.0)
Requires-Dist: requests (>=2.28.1,<3.0.0)
Requires-Dist: rich (>=12.6.0,<13.0.0)
Requires-Dist: rich-click (>=1.5.2,<2.0.0)
Requires-Dist: uvicorn (>=0.20.0,<0.21.0)
Project-URL: Repository, https://github.com/BrandenXia/Random_Img_API
